{"session_id": "true_example", "client_id": "3913872598.9374104736", "visit_date": "2021-05-24", "visit_time": "14:00:00", "visit_number": 5, "utm_source": "kjsLglQLzykiRbcDiGcD", "utm_medium": "organic", "utm_campaign": "LTuZkdKfxRGVceoWkVyg", "utm_adcontent": "JNHcPlZPxEMWDnRiyoBf", "utm_keyword": "(not_set)", "device_category": "mobile", "device_os": "(not_set)", "device_brand": "Apple", "device_model": "(not_set)", "device_screen_resolution": "375x812", "device_browser": "Safari", "geo_country": "Russia", "geo_city": "Saint Petersburg"}